{"name":"pnp-sp-dev-spfx-web-parts-react-3rd-party-api","version":null,"source":"pnp","title":"Consuming Third Party APIs secured with Azure Active Directory within SharePoint Framework","shortDescription":"This sub folders contains a client-side project that shows how to consume a 3rd party API within SharePoint Framework.","longDescription":["This sub folders contains a client-side project that shows how to consume a 3rd party API within SharePoint Framework."],"products":["SharePoint","Office"],"categories":[""],"metadata":[{"key":"CLIENT-SIDE-DEV","value":"React"},{"key":"SPFX-VERSION","value":"1.4.1"}],"thumbnails":[{"type":"image","order":100,"url":"https://github.com/pnp/sp-dev-fx-webparts/raw/master/samples/react-3rd-party-api/images/react-3rd-party-api-ui-sample.gif","alt":"Consuming Third Party APIs secured with Azure Active Directory within SharePoint Framework","slides":null}],"authors":[{"gitHubAccount":"PaoloPia","company":"","pictureUrl":"https://github.com/PaoloPia.png"}],"references":[]}