{
  "$schema": "https://developer.microsoft.com/json-schemas/spfx-build/package-solution.schema.json",
  "solution": {
    "name": "m-365-planner-time-line-web-part-client-side-solution",
    "id": "bfe0b260-4f9c-492f-a591-88be7bd6b427",
    "version": "1.0.0.0",
    "includeClientSideAssets": true,
    "skipFeatureDeployment": true,
    "isDomainIsolated": false,
    "webApiPermissionRequests": [
      {
        "resource": "Microsoft Graph",
        "scope": "User.Read"
      },
      {
        "resource": "Microsoft Graph",
        "scope": "User.Read.All"
      },
      {
        "resource": "Microsoft Graph",
        "scope": "Tasks.ReadWrite"
      },
      {
        "resource": "Microsoft Graph",
        "scope": "GroupMember.Read.All"
      }
    ],
    "developer": {
      "name": "",
      "websiteUrl": "",
      "privacyUrl": "",
      "termsOfUseUrl": "",
      "mpnId": "Undefined-1.20.0"
    },
    "metadata": {
      "shortDescription": {
        "default": "m-365-planner-time-line-web-part description"
      },
      "longDescription": {
        "default": "m-365-planner-time-line-web-part description"
      },
      "screenshotPaths": [],
      "videoUrl": "",
      "categories": []
    },
    "features": [
      {
        "title": "m-365-planner-time-line-web-part Feature",
        "description": "The feature that activates elements of the m-365-planner-time-line-web-part solution.",
        "id": "8e660466-a0f1-43fc-858a-1d37d8e937b1",
        "version": "1.0.0.0"
      }
    ]
  },
  "paths": {
    "zippedPackage": "solution/m-365-planner-time-line-web-part.sppkg"
  }
}
