{
  "@pnp/generator-spfx": {
    "framework": "none",
    "pnpFramework": "none.plus",
    "pnp-libraries": [],
    "pnp-ci": [],
    "pnp-vetting": [],
    "spfxenv": "spo"
  },
  "@microsoft/generator-sharepoint": {
    "environment": "spo",
    "framework": "none",
    "isCreatingSolution": true,
    "version": "1.8.0",
    "libraryName": "git-hub-badge-web-part",
    "libraryId": "d40be93e-575e-419a-a56a-05067c51bfae",
    "packageManager": "npm",
    "isDomainIsolated": false,
    "componentType": "webpart"
  }
}