[
  {
    "name": "pnp-sp-dev-spfx-web-parts-react-my-personal-apps",
    "source": "pnp",
    "title": "My Personal Apps",
    "shortDescription": "The Web Part My Personal Apps allows the user to define links to Applications or Sites for quick access.",
    "url": "https://github.com/pnp/sp-dev-fx-webparts/tree/main/samples/react-my-personal-apps",
    "longDescription": [
      "The Web Part My Personal Apps allows the user to define links to Applications or Sites for quick access."
    ],
    "creationDateTime": "2020-04-28",
    "updateDateTime": "2020-04-28",
    "products": [
      "SharePoint"
    ],
    "metadata": [
      {
        "key": "CLIENT-SIDE-DEV",
        "value": "React"
      },
      {
        "key": "SPFX-VERSION",
        "value": "1.10.0"
      },
      {
        "key": "SPFX-SUPPORTSTHEMEVARIANTS",
        "value": "true"
      },
      {
        "key": "SPFX-TEAMSTAB",
        "value": "true"
      },
      {
        "key": "SPFX-TEAMSPERSONALAPP",
        "value": "true"
      }
    ],
    "thumbnails": [
      {
        "type": "image",
        "order": 100,
        "url": "https://github.com/pnp/sp-dev-fx-webparts/raw/main/samples/react-my-personal-apps/assets/Image1.png",
        "alt": "My Personal Apps"
      },
      {
        "type": "image",
        "order": 101,
        "url": "https://github.com/pnp/sp-dev-fx-webparts/blob/main/samples/react-my-personal-apps/assets/Image06.png?raw=true",
        "alt": "My Personal Apps"
      },
      {
        "type": "image",
        "order": 102,
        "url": "https://github.com/pnp/sp-dev-fx-webparts/blob/main/samples/react-my-personal-apps/assets/Image10.png?raw=true",
        "alt": "My Personal Apps"
      },
      {
        "type": "image",
        "order": 103,
        "url": "https://github.com/pnp/sp-dev-fx-webparts/blob/main/samples/react-my-personal-apps/assets/image11.png?raw=true",
        "alt": "My Personal Apps"
      },
      {
        "type": "image",
        "order": 104,
        "url": "https://github.com/pnp/sp-dev-fx-webparts/blob/main/samples/react-my-personal-apps/assets/image12.png?raw=true",
        "alt": "My Personal Apps"
      },
      {
        "type": "image",
        "order": 105,
        "url": "https://github.com/pnp/sp-dev-fx-webparts/blob/main/samples/react-my-personal-apps/assets/image13.png?raw=true",
        "alt": "My Personal Apps"
      },
      {
        "type": "image",
        "order": 106,
        "url": "https://github.com/pnp/sp-dev-fx-webparts/blob/main/samples/react-my-personal-apps/assets/image14.png?raw=true",
        "alt": "My Personal Apps"
      },
      {
        "type": "image",
        "order": 107,
        "url": "https://github.com/pnp/sp-dev-fx-webparts/blob/main/samples/react-my-personal-apps/assets/Image2.png?raw=true",
        "alt": "My Personal Apps"
      },
      {
        "type": "image",
        "order": 108,
        "url": "https://github.com/pnp/sp-dev-fx-webparts/blob/main/samples/react-my-personal-apps/assets/Image3.png?raw=true",
        "alt": "My Personal Apps"
      },
      {
        "type": "image",
        "order": 109,
        "url": "https://github.com/pnp/sp-dev-fx-webparts/blob/main/samples/react-my-personal-apps/assets/Image4.png?raw=true",
        "alt": "My Personal Apps"
      },
      {
        "type": "image",
        "order": 110,
        "url": "https://github.com/pnp/sp-dev-fx-webparts/blob/main/samples/react-my-personal-apps/assets/Image5.png?raw=true",
        "alt": "My Personal Apps"
      },
      {
        "type": "image",
        "order": 111,
        "url": "https://github.com/pnp/sp-dev-fx-webparts/blob/main/samples/react-my-personal-apps/assets/Image7.png?raw=true",
        "alt": "My Personal Apps"
      },
      {
        "type": "image",
        "order": 112,
        "url": "https://github.com/pnp/sp-dev-fx-webparts/blob/main/samples/react-my-personal-apps/assets/Image8.png?raw=true",
        "alt": "My Personal Apps"
      },
      {
        "type": "image",
        "order": 113,
        "url": "https://github.com/pnp/sp-dev-fx-webparts/blob/main/samples/react-my-personal-apps/assets/Image9.png?raw=true",
        "alt": "My Personal Apps"
      }
    ],
    "authors": [
      {
        "gitHubAccount": "joaojmendes",
        "company": "Storm Technology Ltd",
        "pictureUrl": "https://github.com/joaojmendes.png",
        "name": "Jo\u00E3o Mendes",
        "twitter": "joaojmendes"
      },
      {
        "gitHubAccount": "zachroberts8668",
        "company": "",
        "pictureUrl": "https://github.com/zachroberts8668.png",
        "name": "Zach Roberts"
      }
    ],
    "references": [
      {
        "name": "Build your first SharePoint client-side web part",
        "description": "Client-side web parts are client-side components that run in the context of a SharePoint page. Client-side web parts can be deployed to SharePoint environments that support the SharePoint Framework. You can also use modern JavaScript web frameworks, tools, and libraries to build them.",
        "url": "https://docs.microsoft.com/en-us/sharepoint/dev/spfx/web-parts/get-started/build-a-hello-world-web-part"
      },
      {
        "name": "Supporting section backgrounds",
        "description": "Starting with SharePoint Framework v1.8, web parts can be made aware of any section backgrounds and use these colors to improve the appearance of a web part when hosted in a section with a different background.",
        "url": "https://docs.microsoft.com/en-us/sharepoint/dev/spfx/web-parts/guidance/supporting-section-backgrounds"
      },
      {
        "name": "Building Microsoft Teams Tabs using SharePoint Framework",
        "description": "Starting with SharePoint Framework v1.8, you can build tabs for Microsoft Teams with the SharePoint Framework tooling and use SharePoint as a host for your solutions. As part of the SharePoint Framework v1.10 you can also publish your solution as Microsoft Teams personal app.",
        "url": "https://docs.microsoft.com/en-us/sharepoint/dev/spfx/integrate-with-teams-introduction"
      }
    ]
  }
]