[
  {
    "gitHubAccount": "Paxol",
    "name": "",
    "company": "",
    "pictureUrl": "https://github.com/Paxol.png",
    "avatarSourceUrl": ""
  },
  {
    "gitHubAccount": "aakashbhardwaj619",
    "name": "Aakash Bhardwaj",
    "company": "Microsoft",
    "pictureUrl": "https://avatars.githubusercontent.com/u/33526902?s=460&u=e780f4ef1da922c84f2c5c66c59cecbff2300581&v=4",
    "avatarSourceUrl": ""
  },
  {
    "gitHubAccount": "Abderahman88",
    "name": "Abderahman Moujahid",
    "company": "",
    "pictureUrl": "https://github.com/Abderahman88.png",
    "avatarSourceUrl": ""
  },
  {
    "gitHubAccount": "AbhishekGarg",
    "name": "Abhishek Garg",
    "company": "",
    "pictureUrl": "https://avatars.githubusercontent.com/u/5449154?s=400&v=4",
    "avatarSourceUrl": ""
  },
  {
    "gitHubAccount": "Adam-it",
    "name": "Adam Wójcik",
    "company": "",
    "pictureUrl": "https://github.com/Adam-it.png",
    "avatarSourceUrl": ""
  },
  {
    "gitHubAccount": "AdrianDiaz81",
    "name": "Adrián Díaz",
    "company": "SCRM",
    "pictureUrl": "https://github.com/AdrianDiaz81.png",
    "avatarSourceUrl": ""
  },
  {
    "gitHubAccount": "ahmad-jad-alhak",
    "name": "Ahmad Jad Alhak",
    "company": "",
    "pictureUrl": "https://github.com/ahmad-jad-alhak.png",
    "avatarSourceUrl": ""
  },
  {
    "gitHubAccount": "https://github.com/ahmad-jad-alhak",
    "name": "Ahmad Jad Alhak",
    "company": "",
    "pictureUrl": "https://github.com/ahmad-jad-alhak.png",
    "avatarSourceUrl": ""
  },
  {
    "gitHubAccount": "a1mery",
    "name": "Aimery Thomas",
    "company": "",
    "pictureUrl": "https://github.com/a1mery.png",
    "avatarSourceUrl": ""
  },
  {
    "gitHubAccount": "albegut",
    "name": "Alberto Gutierrez",
    "company": "Hiberus",
    "pictureUrl": "https://github.com/albegut.png",
    "avatarSourceUrl": ""
  },
  {
    "gitHubAccount": "alecwantstobattle",
    "name": "Alec Tecson",
    "company": "",
    "pictureUrl": "https://github.com/alecwantstobattle.png",
    "avatarSourceUrl": ""
  },
  {
    "gitHubAccount": "AlessiaDeMartino",
    "name": "Alessia De Martino",
    "company": "",
    "pictureUrl": "https://github.com/AlessiaDeMartino.png",
    "avatarSourceUrl": ""
  },
  {
    "gitHubAccount": "AJIXuMuK",
    "name": "Alex Terentiev",
    "company": "Sharepointalist",
    "pictureUrl": "https://avatars.githubusercontent.com/u/17036219?s=460&u=b8e83fb70a90eae0c0e0078c206990785e1a5b6f&v=4",
    "avatarSourceUrl": ""
  },
  {
    "gitHubAccount": "ReactIntern",
    "name": "Alison Collins",
    "company": "",
    "pictureUrl": "https://github.com/ReactIntern.png",
    "avatarSourceUrl": ""
  },
  {
    "gitHubAccount": "aaclage",
    "name": "André Lage",
    "company": "",
    "pictureUrl": "https://github.com/aaclage.png",
    "avatarSourceUrl": ""
  },
  {
    "gitHubAccount": "koltyakov",
    "name": "Andrew Koltyakov",
    "company": "ARVO Systems",
    "pictureUrl": "https://avatars.githubusercontent.com/u/7816483?s=460&u=d77bbdeda1e5fc389b11899f93b62a7d00475835&v=4",
    "avatarSourceUrl": ""
  },
  {
    "gitHubAccount": "anoopt",
    "name": "Anoop Tatti",
    "company": "Content +Cloud",
    "pictureUrl": "https://github.com/anoopt.png",
    "avatarSourceUrl": ""
  },
  {
    "gitHubAccount": "Anoop Tatti",
    "name": "anoopt",
    "company": "",
    "pictureUrl": "https://github.com/anoopt.png",
    "avatarSourceUrl": ""
  },
  {
    "gitHubAccount": "anthonyrhopkins",
    "name": "Anthony Hopkins",
    "company": "",
    "pictureUrl": "https://github.com/anthonyrhopkins.png",
    "avatarSourceUrl": ""
  },
  {
    "gitHubAccount": "AriGunawan",
    "name": "Ari Gunawan",
    "company": "",
    "pictureUrl": "https://github.com/AriGunawan.png",
    "avatarSourceUrl": ""
  },
  {
    "gitHubAccount": "arjunumenon",
    "name": "Arjun U Menon",
    "company": "",
    "pictureUrl": "https://github.com/arjunumenon.png",
    "avatarSourceUrl": ""
  },
  {
    "gitHubAccount": "arunkumarperumal",
    "name": "Arun Kumar Perumal",
    "company": "",
    "pictureUrl": "https://avatars.githubusercontent.com/u/39132298?v=4",
    "avatarSourceUrl": ""
  },
  {
    "gitHubAccount": "ashokswain7",
    "name": "Ashok Swain",
    "company": "",
    "pictureUrl": "https://avatars.githubusercontent.com/u/26612087?s=460&v=4",
    "avatarSourceUrl": ""
  },
  {
    "gitHubAccount": "dipongkor",
    "name": "Atish Kumar Dipongkor",
    "company": "Jashore University of Science and Technology",
    "pictureUrl": "https://github.com/dipongkor.png",
    "avatarSourceUrl": ""
  },
  {
    "gitHubAccount": "AustinBreslinDev",
    "name": "Austin Breslin",
    "company": "",
    "pictureUrl": "https://avatars.githubusercontent.com/u/10480670?s=460&v=4",
    "avatarSourceUrl": ""
  },
  {
    "gitHubAccount": "babakdanyal",
    "name": "Babak Danyal",
    "company": "",
    "pictureUrl": "https://github.com/babakdanyal.png",
    "avatarSourceUrl": ""
  },
  {
    "gitHubAccount": "bcameron1231",
    "name": "Beau Cameron",
    "company": "DMI",
    "pictureUrl": "https://avatars.githubusercontent.com/u/7944457?s=460&u=cbea276e0125f71a183f8ad94475dbd1984c6afa&v=4",
    "avatarSourceUrl": ""
  },
  {
    "gitHubAccount": "SPDoctor",
    "name": "Bill Ayers",
    "company": "Flow Simulation Ltd.",
    "pictureUrl": "https://avatars.githubusercontent.com/u/10207194?s=460&v=4",
    "avatarSourceUrl": ""
  },
  {
    "gitHubAccount": "billbrockbank",
    "name": "Bill Brockbank",
    "company": "",
    "pictureUrl": "https://github.com/billbrockbank.png",
    "avatarSourceUrl": ""
  },
  {
    "gitHubAccount": "bogeorge",
    "name": "Bo George",
    "company": "ThreeWill",
    "pictureUrl": "https://avatars.githubusercontent.com/u/10885472?s=460&u=74d23f4289cd555aa530e1c2c6156a382c373f2f&v=4",
    "avatarSourceUrl": ""
  },
  {
    "gitHubAccount": "BobGerman",
    "name": "Bob German",
    "company": "Microsoft",
    "pictureUrl": "https://avatars.githubusercontent.com/u/4664072?s=460&u=29310fd67417ec5f81dc8881dc6eb5dc0065da2d&v=4",
    "avatarSourceUrl": ""
  },
  {
    "gitHubAccount": "bschlintz",
    "name": "Brad Schlintz",
    "company": "Digital Nomad",
    "pictureUrl": "https://github.com/bschlintz.png",
    "avatarSourceUrl": ""
  },
  {
    "gitHubAccount": "brianpmccullough",
    "name": "Brian McCullough",
    "company": "",
    "pictureUrl": "https://github.com/brianpmccullough.png",
    "avatarSourceUrl": ""
  },
  {
    "gitHubAccount": "chakkaradeep",
    "name": "Chakkaradeep Chandran",
    "company": "Microsoft",
    "pictureUrl": "https://avatars.githubusercontent.com/u/7882052?s=460&u=92d546edfe1e1b374c69f0fd9315186eea700b8f&v=4",
    "avatarSourceUrl": ""
  },
  {
    "gitHubAccount": "chandaniprajapati",
    "name": "Chandani Prajapati",
    "company": "Rapid Circle",
    "pictureUrl": "https://github.com/chandaniprajapati.png",
    "avatarSourceUrl": ""
  },
  {
    "gitHubAccount": "thechriskent",
    "name": "Chris Kent",
    "company": "DMI",
    "pictureUrl": "https://avatars.githubusercontent.com/u/8364109?s=460&v=4",
    "avatarSourceUrl": ""
  },
  {
    "gitHubAccount": "ChrisLizon",
    "name": "Chris Lizon",
    "company": "",
    "pictureUrl": "https://github.com/ChrisLizon.png",
    "avatarSourceUrl": ""
  },
  {
    "gitHubAccount": "PathToSharePoint",
    "name": "Christophe Humbert",
    "company": "",
    "pictureUrl": "https://github.com/PathToSharePoint.png",
    "avatarSourceUrl": ""
  },
  {
    "gitHubAccount": "cfernandes-muhimbi",
    "name": "Clavin Fernandes",
    "company": "",
    "pictureUrl": "https://github.com/cfernandes-muhimbi.png",
    "avatarSourceUrl": ""
  },
  {
    "gitHubAccount": "Tanddant",
    "name": "Dan Toft",
    "company": "",
    "pictureUrl": "https://github.com/Tanddant.png",
    "avatarSourceUrl": ""
  },
  {
    "gitHubAccount": "d-turley",
    "name": "Dan Turley",
    "company": "Avanade",
    "pictureUrl": "https://github.com/d-turley.png",
    "avatarSourceUrl": ""
  },
  {
    "gitHubAccount": "dgaeta",
    "name": "Daniel Gaeta",
    "company": "",
    "pictureUrl": "https://avatars.githubusercontent.com/u/1770329?s=460&v=4",
    "avatarSourceUrl": ""
  },
  {
    "gitHubAccount": "danwatford",
    "name": "Daniel Watford",
    "company": "Watford Consulting Ltd.",
    "pictureUrl": "https://avatars.githubusercontent.com/u/5949502?s=460&u=01688c475aa5c94da6a292473ff80ffe1a7975cb&v=4",
    "avatarSourceUrl": ""
  },
  {
    "gitHubAccount": "westerdaled",
    "name": "Daniel Westerdale",
    "company": "Westerdale Solutions Ltd",
    "pictureUrl": "https://avatars.githubusercontent.com/u/937208?s=460&v=4",
    "avatarSourceUrl": ""
  },
  {
    "gitHubAccount": "DanyWyss",
    "name": "Dany Wyss",
    "company": "",
    "pictureUrl": "https://github.com/DanyWyss.png",
    "avatarSourceUrl": ""
  },
  {
    "gitHubAccount": "davidhartman",
    "name": "David Hartman",
    "company": "Slalom",
    "pictureUrl": "https://avatars.githubusercontent.com/u/11304394?s=460&v=4",
    "avatarSourceUrl": ""
  },
  {
    "gitHubAccount": "spdavid",
    "name": "David Opdendries",
    "company": "Zalo Solutions AB",
    "pictureUrl": "https://github.com/spdavid.png",
    "avatarSourceUrl": ""
  },
  {
    "gitHubAccount": "DRamalho92",
    "name": "David Ramalho",
    "company": "Storm Technology",
    "pictureUrl": "https://github.com/DRamalho92.png",
    "avatarSourceUrl": ""
  },
  {
    "gitHubAccount": "PopWarner",
    "name": "David Warner II",
    "company": "Catapult Systems",
    "pictureUrl": "https://avatars.githubusercontent.com/u/10676147?s=460&u=9e4e74223c4ffb430fb77c97892a84b286df1921&v=4",
    "avatarSourceUrl": ""
  },
  {
    "gitHubAccount": "Dhananjay-12",
    "name": "Dhananjay Pant",
    "company": "",
    "pictureUrl": "https://github.com/Dhananjay-12.png",
    "avatarSourceUrl": ""
  },
  {
    "gitHubAccount": "dhavalshah01",
    "name": "Dhaval Shah",
    "company": "",
    "pictureUrl": "https://avatars.githubusercontent.com/u/13947393?s=460&u=38d18e840d22f5567d508027515c728025bae8cb&v=4",
    "avatarSourceUrl": ""
  },
  {
    "gitHubAccount": "Diksha-Bhura",
    "name": "Diksha Bhura",
    "company": "",
    "pictureUrl": "https://github.com/Diksha-Bhura.png",
    "avatarSourceUrl": ""
  },
  {
    "gitHubAccount": "DimchoTsanov",
    "name": "Dimcho Tsanov",
    "company": "",
    "pictureUrl": "https://avatars.githubusercontent.com/u/9058087?s=460&u=43820d97a5aaf5719a4c98be59c673fb460f0001&v=4",
    "avatarSourceUrl": ""
  },
  {
    "gitHubAccount": "dips365",
    "name": "Dipen Shah",
    "company": "",
    "pictureUrl": "https://github.com/dips365.png",
    "avatarSourceUrl": ""
  },
  {
    "gitHubAccount": "divya-akula",
    "name": "Divya Akula",
    "company": "",
    "pictureUrl": "https://github.com/divya-akula.png",
    "avatarSourceUrl": ""
  },
  {
    "gitHubAccount": "DmitryVorobyov",
    "name": "Dmitry Vorobyov",
    "company": "Microsoft",
    "pictureUrl": "https://github.com/DmitryVorobyov.png",
    "avatarSourceUrl": ""
  },
  {
    "gitHubAccount": "DonKirkham",
    "name": "Don Kirkham",
    "company": "Probitas Data Solutions",
    "pictureUrl": "https://github.com/DonKirkham.png",
    "avatarSourceUrl": ""
  },
  {
    "gitHubAccount": "ejazhussain",
    "name": "Ejaz Hussain",
    "company": "Content & Cloud",
    "pictureUrl": "https://github.com/ejazhussain.png",
    "avatarSourceUrl": ""
  },
  {
    "gitHubAccount": "https://github.com/ejazhussain",
    "name": "Ejaz Hussain",
    "company": "",
    "pictureUrl": "https://github.com/ejazhussain.png",
    "avatarSourceUrl": ""
  },
  {
    "gitHubAccount": "Eli-Schei",
    "name": "Eli H. Schei",
    "company": "",
    "pictureUrl": "https://github.com/Eli-Schei.png",
    "avatarSourceUrl": ""
  },
  {
    "gitHubAccount": "estruyf",
    "name": "Elio Struyf",
    "company": "Struyf Consulting",
    "pictureUrl": "https://github.com/estruyf.png",
    "avatarSourceUrl": ""
  },
  {
    "gitHubAccount": "kasuken",
    "name": "Emanuele Bartolesi",
    "company": "",
    "pictureUrl": "https://github.com/kasuken.png",
    "avatarSourceUrl": ""
  },
  {
    "gitHubAccount": "eoverfield",
    "name": "Eric Overfield",
    "company": "PixelMill",
    "pictureUrl": "https://github.com/eoverfield.png",
    "avatarSourceUrl": ""
  },
  {
    "gitHubAccount": "skaggej",
    "name": "Eric Skaggs",
    "company": "",
    "pictureUrl": "https://github.com/skaggej.png",
    "avatarSourceUrl": ""
  },
  {
    "gitHubAccount": "ejbenke",
    "name": "Erik Benke",
    "company": "",
    "pictureUrl": "https://github.com/ejbenke.png",
    "avatarSourceUrl": ""
  },
  {
    "gitHubAccount": "fabiofranzini",
    "name": "Fabio Franzini",
    "company": "",
    "pictureUrl": "https://github.com/fabiofranzini.png",
    "avatarSourceUrl": ""
  },
  {
    "gitHubAccount": "fredupstair",
    "name": "Federico Porceddu",
    "company": "Avanade Italy",
    "pictureUrl": "https://github.com/fredupstair.png",
    "avatarSourceUrl": ""
  },
  {
    "gitHubAccount": "felixbohnacker",
    "name": "Felix Bohnacker",
    "company": "",
    "pictureUrl": "https://github.com/felixbohnacker.png",
    "avatarSourceUrl": ""
  },
  {
    "gitHubAccount": "FranckyC",
    "name": "Franck Cornu",
    "company": "Aequos",
    "pictureUrl": "https://github.com/FranckyC.png",
    "avatarSourceUrl": ""
  },
  {
    "gitHubAccount": "fthorild",
    "name": "Fredrik Thorild",
    "company": "Sogeti Sweden",
    "pictureUrl": "https://github.com/fthorild.png",
    "avatarSourceUrl": ""
  },
  {
    "gitHubAccount": "garrytrinder",
    "name": "Garry Trinder",
    "company": "CPS Global",
    "pictureUrl": "https://github.com/garrytrinder.png",
    "avatarSourceUrl": ""
  },
  {
    "gitHubAccount": "garypretty",
    "name": "Gary Pretty",
    "company": "Microsoft",
    "pictureUrl": "https://github.com/garypretty.png",
    "avatarSourceUrl": ""
  },
  {
    "gitHubAccount": "gauravgoyal5",
    "name": "Gaurav Goyal",
    "company": "BizPortals Solutions",
    "pictureUrl": "https://github.com/gauravgoyal5.png",
    "avatarSourceUrl": ""
  },
  {
    "gitHubAccount": "gautamdsheth",
    "name": "Gautam Sheth",
    "company": "Rapid Circle",
    "pictureUrl": "https://github.com/gautamdsheth.png",
    "avatarSourceUrl": ""
  },
  {
    "gitHubAccount": "giuleon",
    "name": "Giuliano De Luca",
    "company": "",
    "pictureUrl": "https://github.com/giuleon.png",
    "avatarSourceUrl": ""
  },
  {
    "gitHubAccount": "gretchunkim",
    "name": "Gretchun Kim",
    "company": "",
    "pictureUrl": "https://github.com/gretchunkim.png",
    "avatarSourceUrl": ""
  },
  {
    "gitHubAccount": "GuidoZam",
    "name": "Guido Zambarda",
    "company": "PiaSys S.r.l.",
    "pictureUrl": "https://avatars.githubusercontent.com/u/13046662?v=4",
    "avatarSourceUrl": ""
  },
  {
    "gitHubAccount": "GSellier",
    "name": "Guillaume Sellier",
    "company": "Microsoft",
    "pictureUrl": "https://github.com/GSellier.png",
    "avatarSourceUrl": ""
  },
  {
    "gitHubAccount": "HarminderSethi",
    "name": "Harminder Singh",
    "company": "",
    "pictureUrl": "https://github.com/HarminderSethi.png",
    "avatarSourceUrl": ""
  },
  {
    "gitHubAccount": "https://github.com/HarminderSethi",
    "name": "Harminder Singh",
    "company": "",
    "pictureUrl": "https://github.com/HarminderSethi.png",
    "avatarSourceUrl": ""
  },
  {
    "gitHubAccount": "Harsh24491",
    "name": "Harsh Bhavsar",
    "company": "",
    "pictureUrl": "https://github.com/Harsh24491.png",
    "avatarSourceUrl": ""
  },
  {
    "gitHubAccount": "Harshagracy",
    "name": "Harsha Vardhini",
    "company": "",
    "pictureUrl": "https://github.com/Harshagracy.png",
    "avatarSourceUrl": ""
  },
  {
    "gitHubAccount": "hugoabernier",
    "name": "Hugo Bernier",
    "company": "Microsoft",
    "pictureUrl": "https://github.com/hugoabernier.png",
    "avatarSourceUrl": ""
  },
  {
    "gitHubAccount": "jack-vinitsky",
    "name": "Jack Vinitsky",
    "company": "",
    "pictureUrl": "https://github.com/jack-vinitsky.png",
    "avatarSourceUrl": ""
  },
  {
    "gitHubAccount": "Jwaegebaert",
    "name": "Jasey Waegebaert",
    "company": "",
    "pictureUrl": "https://github.com/Jwaegebaert.png",
    "avatarSourceUrl": ""
  },
  {
    "gitHubAccount": "JayakumarB",
    "name": "Jayakumar Balasubramaniam",
    "company": "Hubfly",
    "pictureUrl": "https://github.com/JayakumarB.png",
    "avatarSourceUrl": ""
  },
  {
    "gitHubAccount": "jeffinjacob",
    "name": "Jeffin Jacob",
    "company": "",
    "pictureUrl": "https://github.com/jeffinjacob.png",
    "avatarSourceUrl": ""
  },
  {
    "gitHubAccount": "jeppesc11",
    "name": "Jeppe Spanggaard",
    "company": "",
    "pictureUrl": "https://github.com/jeppesc11.png",
    "avatarSourceUrl": ""
  },
  {
    "gitHubAccount": "jcoleman-pcprofessional",
    "name": "Jeremy Coleman",
    "company": "PC Professional Inc.",
    "pictureUrl": "https://github.com/jcoleman-pcprofessional.png",
    "avatarSourceUrl": ""
  },
  {
    "gitHubAccount": "jerryyasir",
    "name": "Jerry Yasir",
    "company": "DXC Technology",
    "pictureUrl": "https://github.com/jerryyasir.png",
    "avatarSourceUrl": ""
  },
  {
    "gitHubAccount": "joaoferreira",
    "name": "João Ferreira",
    "company": "",
    "pictureUrl": "https://github.com/joaoferreira.png",
    "avatarSourceUrl": ""
  },
  {
    "gitHubAccount": "jtlivio",
    "name": "Joao Livio",
    "company": "",
    "pictureUrl": "https://github.com/jtlivio.png",
    "avatarSourceUrl": ""
  },
  {
    "gitHubAccount": "joaojmendes",
    "name": "João Mendes",
    "company": "Storm Technology Ltd",
    "pictureUrl": "https://github.com/joaojmendes.png",
    "avatarSourceUrl": ""
  },
  {
    "gitHubAccount": "https://github.com/joaojmendes",
    "name": "João Mendes",
    "company": "",
    "pictureUrl": "https://github.com/joaojmendes.png",
    "avatarSourceUrl": ""
  },
  {
    "gitHubAccount": "joelfmrodrigues",
    "name": "Joel Rodrigues",
    "company": "Storm Technology",
    "pictureUrl": "https://github.com/joelfmrodrigues.png",
    "avatarSourceUrl": ""
  },
  {
    "gitHubAccount": "JonasBjerke89",
    "name": "Jonas Bjerke Hansen",
    "company": "",
    "pictureUrl": "https://github.com/JonasBjerke89.png",
    "avatarSourceUrl": ""
  },
  {
    "gitHubAccount": "jquintozamora",
    "name": "Jose Quinto",
    "company": "",
    "pictureUrl": "https://github.com/jquintozamora.png",
    "avatarSourceUrl": ""
  },
  {
    "gitHubAccount": "juliemturner",
    "name": "Julie Turner",
    "company": "",
    "pictureUrl": "https://github.com/juliemturner.png",
    "avatarSourceUrl": ""
  },
  {
    "gitHubAccount": "djsladi",
    "name": "Kalle Mansikkaniemi",
    "company": "",
    "pictureUrl": "https://github.com/djsladi.png",
    "avatarSourceUrl": ""
  },
  {
    "gitHubAccount": "KEMiCZA",
    "name": "Kemal Sinanagic",
    "company": "Ventigrate",
    "pictureUrl": "https://github.com/KEMiCZA.png",
    "avatarSourceUrl": ""
  },
  {
    "gitHubAccount": "kmees",
    "name": "Kevin Mees",
    "company": "",
    "pictureUrl": "https://github.com/kmees.png",
    "avatarSourceUrl": ""
  },
  {
    "gitHubAccount": "kkazala",
    "name": "Kinga Kazala",
    "company": "",
    "pictureUrl": "https://github.com/kkazala.png",
    "avatarSourceUrl": ""
  },
  {
    "gitHubAccount": "kunj-sangani",
    "name": "Kunj Sangani",
    "company": "",
    "pictureUrl": "https://github.com/kunj-sangani.png",
    "avatarSourceUrl": ""
  },
  {
    "gitHubAccount": "LauraKokkarinen",
    "name": "Laura Kokkarinen",
    "company": "Sulava",
    "pictureUrl": "https://github.com/LauraKokkarinen.png",
    "avatarSourceUrl": ""
  },
  {
    "gitHubAccount": "koskimiesl",
    "name": "Lauri Koskimies",
    "company": "",
    "pictureUrl": "https://github.com/koskimiesl.png",
    "avatarSourceUrl": ""
  },
  {
    "gitHubAccount": "ChinHoongLew",
    "name": "Lew Chin Hoong",
    "company": "",
    "pictureUrl": "https://github.com/ChinHoongLew.png",
    "avatarSourceUrl": ""
  },
  {
    "gitHubAccount": "flowerbot",
    "name": "Linda K",
    "company": "",
    "pictureUrl": "https://github.com/flowerbot.png",
    "avatarSourceUrl": ""
  },
  {
    "gitHubAccount": "luismanez",
    "name": "Luis Mañez",
    "company": "ClearPeople",
    "pictureUrl": "https://github.com/luismanez.png",
    "avatarSourceUrl": ""
  },
  {
    "gitHubAccount": "levalencia",
    "name": "Luis Valencia",
    "company": "",
    "pictureUrl": "https://github.com/levalencia.png",
    "avatarSourceUrl": ""
  },
  {
    "gitHubAccount": "LuiseFreese",
    "name": "Luise Freese",
    "company": "",
    "pictureUrl": "https://github.com/LuiseFreese.png",
    "avatarSourceUrl": ""
  },
  {
    "gitHubAccount": "Maya-Mostafa",
    "name": "Mai Mostafa",
    "company": "",
    "pictureUrl": "https://github.com/Maya-Mostafa.png",
    "avatarSourceUrl": ""
  },
  {
    "gitHubAccount": "msekkappan",
    "name": "Malathi Sekkappan",
    "company": "Microsoft",
    "pictureUrl": "https://github.com/msekkappan.png",
    "avatarSourceUrl": ""
  },
  {
    "gitHubAccount": "maschroeder-z",
    "name": "Marc André Schröder-Zhou",
    "company": "",
    "pictureUrl": "https://github.com/maschroeder-z.png",
    "avatarSourceUrl": ""
  },
  {
    "gitHubAccount": "https://github.com/maschroeder-z",
    "name": "Marc André Schröder-Zhou",
    "company": "",
    "pictureUrl": "https://github.com/maschroeder-z.png",
    "avatarSourceUrl": ""
  },
  {
    "gitHubAccount": "mgwojciech",
    "name": "Marcin Wojciechowski",
    "company": "Valo",
    "pictureUrl": "https://github.com/mgwojciech.png",
    "avatarSourceUrl": ""
  },
  {
    "gitHubAccount": "mmsharepoint",
    "name": "Markus Moeller",
    "company": "Avanade ",
    "pictureUrl": "https://github.com/mmsharepoint.png",
    "avatarSourceUrl": ""
  },
  {
    "gitHubAccount": "MartinHatch",
    "name": "Martin Hatch",
    "company": "",
    "pictureUrl": "https://github.com/MartinHatch.png",
    "avatarSourceUrl": ""
  },
  {
    "gitHubAccount": "martinlingstuyl",
    "name": "Martin Lingstuyl",
    "company": "I4-YOU Business Solutions b.v.",
    "pictureUrl": "https://github.com/martinlingstuyl.png",
    "avatarSourceUrl": ""
  },
  {
    "gitHubAccount": "mjimison",
    "name": "Matt Jimison",
    "company": "Allegient",
    "pictureUrl": "https://github.com/mjimison.png",
    "avatarSourceUrl": ""
  },
  {
    "gitHubAccount": "mpaukkon",
    "name": "Matti Paukkonen",
    "company": "",
    "pictureUrl": "https://github.com/mpaukkon.png",
    "avatarSourceUrl": ""
  },
  {
    "gitHubAccount": "michaelmaillot",
    "name": "Michaël Maillot",
    "company": "onepoint",
    "pictureUrl": "https://github.com/michaelmaillot.png",
    "avatarSourceUrl": ""
  },
  {
    "gitHubAccount": "mkm17",
    "name": "Michał Kornet",
    "company": "",
    "pictureUrl": "https://github.com/mkm17.png",
    "avatarSourceUrl": ""
  },
  {
    "gitHubAccount": "mromiszewski",
    "name": "Michał Romiszewski",
    "company": "",
    "pictureUrl": "https://github.com/mromiszewski.png",
    "avatarSourceUrl": ""
  },
  {
    "gitHubAccount": "10xMike",
    "name": "Michele Catena",
    "company": "",
    "pictureUrl": "https://github.com/10xMike.png",
    "avatarSourceUrl": ""
  },
  {
    "gitHubAccount": "pnp",
    "name": "Microsoft 365 & Power Platform Community",
    "company": "",
    "pictureUrl": "https://github.com/pnp.png",
    "avatarSourceUrl": ""
  },
  {
    "gitHubAccount": "wobba",
    "name": "Mikael Svenson",
    "company": "Microsoft",
    "pictureUrl": "https://github.com/wobba.png",
    "avatarSourceUrl": ""
  },
  {
    "gitHubAccount": "mhomol",
    "name": "Mike Homol",
    "company": "ThreeWill",
    "pictureUrl": "https://github.com/mhomol.png",
    "avatarSourceUrl": ""
  },
  {
    "gitHubAccount": "thespooler",
    "name": "Mike Myers",
    "company": "",
    "pictureUrl": "https://github.com/thespooler.png",
    "avatarSourceUrl": ""
  },
  {
    "gitHubAccount": "mikezimm",
    "name": "Mike Zimmerman",
    "company": "",
    "pictureUrl": "https://github.com/mikezimm.png",
    "avatarSourceUrl": ""
  },
  {
    "gitHubAccount": "milanholemans",
    "name": "Milan Holemans",
    "company": "",
    "pictureUrl": "https://github.com/milanholemans.png",
    "avatarSourceUrl": ""
  },
  {
    "gitHubAccount": "derhallim",
    "name": "Mohamed Derhalli",
    "company": "",
    "pictureUrl": "https://github.com/derhallim.png",
    "avatarSourceUrl": ""
  },
  {
    "gitHubAccount": "mohammadamer",
    "name": "Mohammad Amer",
    "company": "Atea Global Services",
    "pictureUrl": "https://github.com/mohammadamer.png",
    "avatarSourceUrl": ""
  },
  {
    "gitHubAccount": "Mahyar915",
    "name": "Mohammad Mahyar Pourabdollah Khadar",
    "company": "",
    "pictureUrl": "https://github.com/Mahyar915.png",
    "avatarSourceUrl": ""
  },
  {
    "gitHubAccount": "mrkhandev",
    "name": "mrkhandev",
    "company": "",
    "pictureUrl": "https://github.com/mrkhandev.png",
    "avatarSourceUrl": ""
  },
  {
    "gitHubAccount": "nanddeepn",
    "name": "Nanddeep Nachan",
    "company": "",
    "pictureUrl": "https://github.com/nanddeepn.png",
    "avatarSourceUrl": ""
  },
  {
    "gitHubAccount": "nbarkhina",
    "name": "Neil Barkhina",
    "company": "",
    "pictureUrl": "https://github.com/nbarkhina.png",
    "avatarSourceUrl": ""
  },
  {
    "gitHubAccount": "ferrarirosso",
    "name": "Nello D'Andrea",
    "company": "",
    "pictureUrl": "https://github.com/ferrarirosso.png",
    "avatarSourceUrl": ""
  },
  {
    "gitHubAccount": "nemortu",
    "name": "nemortu",
    "company": "",
    "pictureUrl": "https://github.com/nemortu.png",
    "avatarSourceUrl": ""
  },
  {
    "gitHubAccount": "techienickb",
    "name": "Nick Brown",
    "company": "",
    "pictureUrl": "https://github.com/techienickb.png",
    "avatarSourceUrl": ""
  },
  {
    "gitHubAccount": "nicodecleyre",
    "name": "Nico De Cleyre",
    "company": "",
    "pictureUrl": "https://github.com/nicodecleyre.png",
    "avatarSourceUrl": ""
  },
  {
    "gitHubAccount": "NicolasKheirallah",
    "name": "Nicolas Kheirallah",
    "company": "Exobe",
    "pictureUrl": "https://github.com/NicolasKheirallah.png",
    "avatarSourceUrl": ""
  },
  {
    "gitHubAccount": "https://github.com/NicolasKheirallah",
    "name": "Nicolas Kheirallah",
    "company": "",
    "pictureUrl": "https://github.com/NicolasKheirallah.png",
    "avatarSourceUrl": ""
  },
  {
    "gitHubAccount": "ICTNiklasWilhelm",
    "name": "Niklas Wilhelm",
    "company": "",
    "pictureUrl": "https://github.com/ICTNiklasWilhelm.png",
    "avatarSourceUrl": ""
  },
  {
    "gitHubAccount": "NishkalankBezawada",
    "name": "NIshkalank Bezawada (MVP)",
    "company": "Bravero AB",
    "pictureUrl": "https://github.com/NishkalankBezawada.png",
    "avatarSourceUrl": ""
  },
  {
    "gitHubAccount": "olegrumiancev",
    "name": "Oleg Rumiancev",
    "company": "",
    "pictureUrl": "https://github.com/olegrumiancev.png",
    "avatarSourceUrl": ""
  },
  {
    "gitHubAccount": "OlivierCC",
    "name": "Olivier Carpentier",
    "company": "Microsoft",
    "pictureUrl": "https://github.com/OlivierCC.png",
    "avatarSourceUrl": ""
  },
  {
    "gitHubAccount": "omarelanis",
    "name": "Omar El-Anis",
    "company": "",
    "pictureUrl": "https://github.com/omarelanis.png",
    "avatarSourceUrl": ""
  },
  {
    "gitHubAccount": "PaoloPia",
    "name": "Paolo Pialorsi",
    "company": "PiaSys.com",
    "pictureUrl": "https://github.com/PaoloPia.png",
    "avatarSourceUrl": ""
  },
  {
    "gitHubAccount": "patrick-rodgers",
    "name": "Patrick Rodgers",
    "company": "Microsoft",
    "pictureUrl": "https://github.com/patrick-rodgers.png",
    "avatarSourceUrl": ""
  },
  {
    "gitHubAccount": "pmatthews05",
    "name": "Paul Matthews",
    "company": "CF Code",
    "pictureUrl": "https://github.com/pmatthews05.png",
    "avatarSourceUrl": ""
  },
  {
    "gitHubAccount": "paulryan",
    "name": "Paul Ryan",
    "company": "",
    "pictureUrl": "https://github.com/paulryan.png",
    "avatarSourceUrl": ""
  },
  {
    "gitHubAccount": "pschaeflein",
    "name": "Paul Schaeflein",
    "company": "AddIn365",
    "pictureUrl": "https://github.com/pschaeflein.png",
    "avatarSourceUrl": ""
  },
  {
    "gitHubAccount": "perr124",
    "name": "Perry Kankam",
    "company": "",
    "pictureUrl": "https://github.com/perr124.png",
    "avatarSourceUrl": ""
  },
  {
    "gitHubAccount": "petkir",
    "name": "Peter Paul Kirschner",
    "company": "ACP Cubido",
    "pictureUrl": "https://github.com/petkir.png",
    "avatarSourceUrl": ""
  },
  {
    "gitHubAccount": "PieterHeemeryck",
    "name": "Pieter Heemeryck",
    "company": "",
    "pictureUrl": "https://github.com/PieterHeemeryck.png",
    "avatarSourceUrl": ""
  },
  {
    "gitHubAccount": "DingmaomaoBJTU",
    "name": "Qiong Wu",
    "company": "Microsoft",
    "pictureUrl": "https://github.com/DingmaomaoBJTU.png",
    "avatarSourceUrl": ""
  },
  {
    "gitHubAccount": "rabwill",
    "name": "Rabia Williams",
    "company": "Microsoft",
    "pictureUrl": "https://github.com/rabwill.png",
    "avatarSourceUrl": ""
  },
  {
    "gitHubAccount": "rahulsuryawanshi",
    "name": "Rahul Suryawanshi",
    "company": "",
    "pictureUrl": "https://github.com/rahulsuryawanshi.png",
    "avatarSourceUrl": ""
  },
  {
    "gitHubAccount": "rjesh-git",
    "name": "Rajesh Sitaraman",
    "company": "CoreBTS",
    "pictureUrl": "https://github.com/rjesh-git.png",
    "avatarSourceUrl": ""
  },
  {
    "gitHubAccount": "RamPrasadMeenavalli",
    "name": "Ram Prasad Meenavalli",
    "company": "",
    "pictureUrl": "https://github.com/RamPrasadMeenavalli.png",
    "avatarSourceUrl": ""
  },
  {
    "gitHubAccount": "Ramakrishnan24689",
    "name": "Ramakrishnan Raman",
    "company": "Microsoft",
    "pictureUrl": "https://github.com/Ramakrishnan24689.png",
    "avatarSourceUrl": ""
  },
  {
    "gitHubAccount": "AhmadiRamin",
    "name": "Ramin Ahmadi",
    "company": "Content and Cloud",
    "pictureUrl": "https://github.com/AhmadiRamin.png",
    "avatarSourceUrl": ""
  },
  {
    "gitHubAccount": "ramin-ahmadi",
    "name": "Ramin Ahmadi",
    "company": "",
    "pictureUrl": "https://github.com/ramin-ahmadi.png",
    "avatarSourceUrl": ""
  },
  {
    "gitHubAccount": "Ravikadri",
    "name": "Ravi Chandra",
    "company": "Netwoven",
    "pictureUrl": "https://github.com/Ravikadri.png",
    "avatarSourceUrl": ""
  },
  {
    "gitHubAccount": "ravi16a87",
    "name": "Ravi Kulkarni",
    "company": "Cognizant",
    "pictureUrl": "https://github.com/ravi16a87.png",
    "avatarSourceUrl": ""
  },
  {
    "gitHubAccount": "brk114",
    "name": "Ravi Kumar Bomma",
    "company": "TechDimension IT Solutions",
    "pictureUrl": "https://github.com/brk114.png",
    "avatarSourceUrl": ""
  },
  {
    "gitHubAccount": "ravichandran-blog",
    "name": "Ravichandran Krishnasamy",
    "company": "Content Formula",
    "pictureUrl": "https://github.com/ravichandran-blog.png",
    "avatarSourceUrl": ""
  },
  {
    "gitHubAccount": "renatoromao",
    "name": "Renato Romão",
    "company": "",
    "pictureUrl": "https://github.com/renatoromao.png",
    "avatarSourceUrl": ""
  },
  {
    "gitHubAccount": "reshmee011",
    "name": "Reshmee Auckloo",
    "company": "",
    "pictureUrl": "https://github.com/reshmee011.png",
    "avatarSourceUrl": ""
  },
  {
    "gitHubAccount": "rishabhshukla12",
    "name": "Rishabh Shukla",
    "company": "",
    "pictureUrl": "https://github.com/rishabhshukla12.png",
    "avatarSourceUrl": ""
  },
  {
    "gitHubAccount": "rfjschouten",
    "name": "Robert Schouten",
    "company": "Wortell",
    "pictureUrl": "https://github.com/rfjschouten.png",
    "avatarSourceUrl": ""
  },
  {
    "gitHubAccount": "agtenr",
    "name": "Robin Agten",
    "company": "",
    "pictureUrl": "https://github.com/agtenr.png",
    "avatarSourceUrl": ""
  },
  {
    "gitHubAccount": "robinmeure",
    "name": "Robin Meure",
    "company": "",
    "pictureUrl": "https://github.com/robinmeure.png",
    "avatarSourceUrl": ""
  },
  {
    "gitHubAccount": "na",
    "name": "Rodrigo Silva",
    "company": "",
    "pictureUrl": "https://github.com/RodrigoSilva.png",
    "avatarSourceUrl": ""
  },
  {
    "gitHubAccount": "roldengarm",
    "name": "Roland Oldengarm",
    "company": "",
    "pictureUrl": "https://github.com/roldengarm.png",
    "avatarSourceUrl": ""
  },
  {
    "gitHubAccount": "ruslan-s",
    "name": "ruslan-s",
    "company": "",
    "pictureUrl": "https://github.com/ruslan-s.png",
    "avatarSourceUrl": ""
  },
  {
    "gitHubAccount": "russgove",
    "name": "Russell Gove",
    "company": "",
    "pictureUrl": "https://github.com/russgove.png",
    "avatarSourceUrl": ""
  },
  {
    "gitHubAccount": "sharepointknight",
    "name": "Ryan Schouten",
    "company": "",
    "pictureUrl": "https://github.com/sharepointknight.png",
    "avatarSourceUrl": ""
  },
  {
    "gitHubAccount": "saiiiiiii",
    "name": "Sai Siva Ram Bandaru",
    "company": "",
    "pictureUrl": "https://github.com/saiiiiiii.png",
    "avatarSourceUrl": ""
  },
  {
    "gitHubAccount": "smaity",
    "name": "Sajal Maity",
    "company": "JP Morgan Chase",
    "pictureUrl": "https://github.com/smaity.png",
    "avatarSourceUrl": ""
  },
  {
    "gitHubAccount": "salascz",
    "name": "salascz",
    "company": "",
    "pictureUrl": "https://github.com/salascz.png",
    "avatarSourceUrl": ""
  },
  {
    "gitHubAccount": "SamC148",
    "name": "Sam Collins",
    "company": "",
    "pictureUrl": "https://github.com/SamC148.png",
    "avatarSourceUrl": ""
  },
  {
    "gitHubAccount": "Sandeep-FED",
    "name": "Sandeep P S",
    "company": "EY",
    "pictureUrl": "https://github.com/sandeep-fed.png",
    "avatarSourceUrl": ""
  },
  {
    "gitHubAccount": "https://github.com/Sandeep-FED",
    "name": "Sandeep P S",
    "company": "",
    "pictureUrl": "https://github.com/Sandeep-FED.png",
    "avatarSourceUrl": ""
  },
  {
    "gitHubAccount": "SandeepDev365",
    "name": "Sandeep Unnikrishnan",
    "company": "",
    "pictureUrl": "https://github.com/SandeepDev365.png",
    "avatarSourceUrl": ""
  },
  {
    "gitHubAccount": "sauslash",
    "name": "Saulo Oliveira",
    "company": "",
    "pictureUrl": "https://github.com/sauslash.png",
    "avatarSourceUrl": ""
  },
  {
    "gitHubAccount": "saurabh7019",
    "name": "Saurabh Tripathi",
    "company": "",
    "pictureUrl": "https://github.com/saurabh7019.png",
    "avatarSourceUrl": ""
  },
  {
    "gitHubAccount": "sebastienlevert",
    "name": "Sébastien Levert",
    "company": "Microsoft",
    "pictureUrl": "https://github.com/sebastienlevert.png",
    "avatarSourceUrl": ""
  },
  {
    "gitHubAccount": "serdarketenci",
    "name": "Serdar Ketenci",
    "company": "",
    "pictureUrl": "https://github.com/serdarketenci.png",
    "avatarSourceUrl": ""
  },
  {
    "gitHubAccount": "s-KaiNet",
    "name": "Sergei Sergeev",
    "company": "Mastaq",
    "pictureUrl": "https://github.com/s-KaiNet.png",
    "avatarSourceUrl": ""
  },
  {
    "gitHubAccount": "SPFxAppDev",
    "name": "Sergej Schwabauer",
    "company": "",
    "pictureUrl": "https://github.com/SPFxAppDev.png",
    "avatarSourceUrl": ""
  },
  {
    "gitHubAccount": "wideserg",
    "name": "Sergey Shiroky",
    "company": "",
    "pictureUrl": "https://github.com/wideserg.png",
    "avatarSourceUrl": ""
  },
  {
    "gitHubAccount": "siddharth-vaghasia",
    "name": "Siddharth Vaghasia",
    "company": "",
    "pictureUrl": "https://github.com/siddharth-vaghasia.png",
    "avatarSourceUrl": ""
  },
  {
    "gitHubAccount": "simonagren",
    "name": "Simon Ågren",
    "company": "Sogeti",
    "pictureUrl": "https://github.com/simonagren.png",
    "avatarSourceUrl": ""
  },
  {
    "gitHubAccount": "spplante",
    "name": "Simon-Pierre Plante",
    "company": "SPP Technologies",
    "pictureUrl": "https://github.com/spplante.png",
    "avatarSourceUrl": ""
  },
  {
    "gitHubAccount": "SlowRobot",
    "name": "SlowRobot",
    "company": "",
    "pictureUrl": "https://github.com/SlowRobot.png",
    "avatarSourceUrl": ""
  },
  {
    "gitHubAccount": "SmitaNachan",
    "name": "Smita Nachan",
    "company": "",
    "pictureUrl": "https://github.com/SmitaNachan.png",
    "avatarSourceUrl": ""
  },
  {
    "gitHubAccount": "StfBauer",
    "name": "Stefan Bauer",
    "company": "N8D",
    "pictureUrl": "https://github.com/StfBauer.png",
    "avatarSourceUrl": ""
  },
  {
    "gitHubAccount": "stephanbisser",
    "name": "Stephan Bisser",
    "company": "",
    "pictureUrl": "https://github.com/stephanbisser.png",
    "avatarSourceUrl": ""
  },
  {
    "gitHubAccount": "sudeepghatak",
    "name": "Sudeep Ghatak",
    "company": "",
    "pictureUrl": "https://github.com/sudeepghatak.png",
    "avatarSourceUrl": ""
  },
  {
    "gitHubAccount": "sudharsank",
    "name": "Sudharsan K.",
    "company": "NTT Ltd",
    "pictureUrl": "https://github.com/sudharsank.png",
    "avatarSourceUrl": ""
  },
  {
    "gitHubAccount": "sudhir007rawat",
    "name": "Sudhir Rawat",
    "company": "HCL America",
    "pictureUrl": "https://github.com/sudhir007rawat.png",
    "avatarSourceUrl": ""
  },
  {
    "gitHubAccount": "365knoten",
    "name": "Sven Sieverding",
    "company": "Storm Technology Ltd",
    "pictureUrl": "https://github.com/365knoten.png",
    "avatarSourceUrl": ""
  },
  {
    "gitHubAccount": "Swaminathan-Sriram",
    "name": "Swaminathan Sriram",
    "company": "",
    "pictureUrl": "https://github.com/Swaminathan-Sriram.png",
    "avatarSourceUrl": ""
  },
  {
    "gitHubAccount": "karamem0",
    "name": "Takashi Shinohara",
    "company": "",
    "pictureUrl": "https://github.com/karamem0.png",
    "avatarSourceUrl": ""
  },
  {
    "gitHubAccount": "tom-daly",
    "name": "Thomas Daly",
    "company": "SoHo Dragon",
    "pictureUrl": "https://github.com/tom-daly.png",
    "avatarSourceUrl": ""
  },
  {
    "gitHubAccount": "tmaestrini",
    "name": "Tobias Maestrini",
    "company": "",
    "pictureUrl": "https://github.com/tmaestrini.png",
    "avatarSourceUrl": ""
  },
  {
    "gitHubAccount": "TBag",
    "name": "Todd Baginski",
    "company": "Canviz LLC",
    "pictureUrl": "https://github.com/TBag.png",
    "avatarSourceUrl": ""
  },
  {
    "gitHubAccount": "tristian2",
    "name": "Tristian O'brien",
    "company": "",
    "pictureUrl": "https://github.com/tristian2.png",
    "avatarSourceUrl": ""
  },
  {
    "gitHubAccount": "tvahk",
    "name": "tvahk",
    "company": "",
    "pictureUrl": "https://github.com/tvahk.png",
    "avatarSourceUrl": ""
  },
  {
    "gitHubAccount": "ValerasNarbutas",
    "name": "Valeras Narbutas",
    "company": "Macaw",
    "pictureUrl": "https://github.com/ValerasNarbutas.png",
    "avatarSourceUrl": ""
  },
  {
    "gitHubAccount": "vman",
    "name": "Vardhaman Deshpande",
    "company": "",
    "pictureUrl": "https://github.com/vman.png",
    "avatarSourceUrl": ""
  },
  {
    "gitHubAccount": "VelinGeorgiev",
    "name": "Velin Georgiev",
    "company": "",
    "pictureUrl": "https://github.com/VelinGeorgiev.png",
    "avatarSourceUrl": ""
  },
  {
    "gitHubAccount": "VenkadeshSundaramurthy",
    "name": "Venkadesh Sundaramurthy",
    "company": "",
    "pictureUrl": "https://github.com/VenkadeshSundaramurthy.png",
    "avatarSourceUrl": ""
  },
  {
    "gitHubAccount": "VesaJuvonen",
    "name": "Vesa Juvonen",
    "company": "Microsoft",
    "pictureUrl": "https://github.com/VesaJuvonen.png",
    "avatarSourceUrl": ""
  },
  {
    "gitHubAccount": "baywet",
    "name": "Vincent Biret",
    "company": "Microsoft",
    "pictureUrl": "https://github.com/baywet.png",
    "avatarSourceUrl": ""
  },
  {
    "gitHubAccount": "vipulkelkar",
    "name": "Vipul Kelkar",
    "company": "Rapid Circle",
    "pictureUrl": "https://github.com/vipulkelkar.png",
    "avatarSourceUrl": ""
  },
  {
    "gitHubAccount": "Vivekrajput20",
    "name": "Vivek Chand",
    "company": "",
    "pictureUrl": "https://github.com/Vivekrajput20.png",
    "avatarSourceUrl": ""
  },
  {
    "gitHubAccount": "waldekmastykarz",
    "name": "Waldek Mastykarz",
    "company": "Microsoft",
    "pictureUrl": "https://github.com/waldekmastykarz.png",
    "avatarSourceUrl": ""
  },
  {
    "gitHubAccount": "xiao-lix",
    "name": "Xiao Li",
    "company": "Microsoft",
    "pictureUrl": "https://github.com/xiao-lix.png",
    "avatarSourceUrl": ""
  },
  {
    "gitHubAccount": "YannickRe",
    "name": "Yannick Reekmans",
    "company": "",
    "pictureUrl": "https://github.com/YannickRe.png",
    "avatarSourceUrl": ""
  },
  {
    "gitHubAccount": "yhabersaat",
    "name": "Yves Habersaat",
    "company": "",
    "pictureUrl": "https://github.com/yhabersaat.png",
    "avatarSourceUrl": ""
  },
  {
    "gitHubAccount": "zachroberts8668",
    "name": "Zach Roberts",
    "company": "",
    "pictureUrl": "https://github.com/zachroberts8668.png",
    "avatarSourceUrl": ""
  }
]